adafruit_circuitpython_magtag-2.2.16.dist-info/licenses/LICENSE
adafruit_magtag/__init__.py
adafruit_magtag/graphics.py
adafruit_magtag/magtag.py
adafruit_magtag/network.py
adafruit_magtag/peripherals.py
adafruit_circuitpython_magtag-2.2.16.dist-info/METADATA
adafruit_circuitpython_magtag-2.2.16.dist-info/WHEEL
adafruit_circuitpython_magtag-2.2.16.dist-info/top_level.txt
adafruit_circuitpython_magtag-2.2.16.dist-info/RECORD
