Metadata-Version: 2.4
Name: adafruit-circuitpython-magtag
Version: 2.2.16
Summary: Helper library for the Adafruit MagTag
Author-email: Adafruit Industries <circuitpython@adafruit.com>
License: MIT
Project-URL: Homepage, https://github.com/adafruit/Adafruit_CircuitPython_MagTag
Keywords: adafruit,magtag,eink,iot,esp32,espressif,hardware,micropythoncircuitpython
Classifier: Intended Audience :: Developers
Classifier: Topic :: Software Development :: Libraries
Classifier: Topic :: Software Development :: Embedded Systems
Classifier: Topic :: System :: Hardware
Classifier: License :: OSI Approved :: MIT License
Classifier: Programming Language :: Python :: 3
License-File: LICENSE
Requires-Dist: Adafruit-Blinka-displayio
Requires-Dist: Adafruit-Blinka
Requires-Dist: adafruit-circuitpython-requests
Requires-Dist: adafruit-circuitpython-neopixel
Requires-Dist: adafruit-circuitpython-simpleio
Requires-Dist: adafruit-circuitpython-portalbase
Provides-Extra: optional
Dynamic: license-file
